pygame_toolkit
