Metadata-Version: 2.1
Name: pgtk
Version: 0.0.1.5
Summary: Provides some simple functionalities using pygame
Home-page: UNKNOWN
Author: Vinicius Putti Morais
Author-email: viniputtim@gmail.com
License: MIT license
Keywords: pygame
Platform: UNKNOWN
License-File: LICENSE
